xval/__init__.py
xval/api.py
xval/cli.py
xval/config.py
xval/commands/__init__.py
xval/commands/users.py
xval/commands/val.py
xval/examples/clone_run_and_audit.py
xval-0.0.6.dist-info/METADATA
xval-0.0.6.dist-info/WHEEL
xval-0.0.6.dist-info/entry_points.txt
xval-0.0.6.dist-info/top_level.txt
xval-0.0.6.dist-info/RECORD
