Metadata-Version: 2.4
Name: xval
Version: 0.0.6
Summary: Xval's Python SDK and CLI
Author-email: Timothy Quast <timothy.quast@xval.io>
License: MIT
Keywords: xval,xact,actuary,actuarial,valuation
Classifier: Programming Language :: Python :: 3
Classifier: Operating System :: OS Independent
Requires-Dist: click==8.1.8
Requires-Dist: colorama==0.4.6
Requires-Dist: markdown-it-py==3.0.0
Requires-Dist: mdurl==0.1.2
Requires-Dist: Pygments==2.19.1
Requires-Dist: rich==14.0.0
Requires-Dist: shellingham==1.5.4
Requires-Dist: typer==0.15.2
Requires-Dist: typing_extensions==4.13.1
Requires-Dist: certifi==2025.1.31
Requires-Dist: charset-normalizer==3.4.1
Requires-Dist: idna==3.10
Requires-Dist: requests==2.32.3
Requires-Dist: urllib3==2.3.0
Requires-Dist: prompt_toolkit==3.0.50
Requires-Dist: questionary==2.1.0
Requires-Dist: wcwidth==0.2.13
